{
	"info": {
		"_postman_id": "5ee6b907-da31-468f-b3ce-400ff821ba19",
		"name": "New Collection",
		"schema": "https://schema.getpostman.com/json/collection/v2.1.0/collection.json"
	},
	"item": [
		{
			"name": "most popular repos sorted by numbers of stars with  or without limited number of repos",
			"request": {
				"method": "GET",
				"header": [],
				"url": {
					"raw": "http://localhost:8000?per_page=100",
					"protocol": "http",
					"host": [
						"localhost"
					],
					"port": "8000",
					"query": [
						{
							"key": "per_page",
							"value": "100"
						}
					]
				}
			},
			"response": []
		},
		{
			"name": "most popular created from date onward",
			"request": {
				"method": "GET",
				"header": [],
				"url": {
					"raw": "http://localhost:8000?created:>2019-01-10",
					"protocol": "http",
					"host": [
						"localhost"
					],
					"port": "8000",
					"query": [
						{
							"key": "created:>2019-01-10",
							"value": null
						}
					]
				}
			},
			"response": []
		},
		{
			"name": "filter with programming languages",
			"request": {
				"method": "GET",
				"header": [],
				"url": {
					"raw": "http://localhost:8000?language:go",
					"protocol": "http",
					"host": [
						"localhost"
					],
					"port": "8000",
					"query": [
						{
							"key": "language:go",
							"value": null
						}
					]
				}
			},
			"response": []
		}
	]
}